CapiPy/GUI.py
CapiPy/__init__.py
CapiPy/__main__.py
CapiPy/ncfiles/CapiPy.png
CapiPy/ncfiles/settings_file.cfg
CapiPy/src/AS_ID.py
CapiPy/src/BMOD.py
CapiPy/src/ClusterDistance.py
CapiPy/src/QUAT.py
CapiPy/src/Ref_retrieval.py
CapiPy/src/S2_analysis.py
CapiPy/src/__init__.py
CapiPy/src/__pycache__/AS_ID.cpython-38.pyc
CapiPy/src/__pycache__/BMOD.cpython-38.pyc
CapiPy/src/__pycache__/ClusterDistance.cpython-38.pyc
CapiPy/src/__pycache__/QUAT.cpython-38.pyc
CapiPy/src/__pycache__/Ref_retrieval.cpython-38.pyc
CapiPy/src/__pycache__/S2_analysis.cpython-38.pyc
CapiPy/src/__pycache__/__init__.cpython-38.pyc
CapiPy-0.1.1.dist-info/LICENSE
CapiPy-0.1.1.dist-info/METADATA
CapiPy-0.1.1.dist-info/WHEEL
CapiPy-0.1.1.dist-info/top_level.txt
CapiPy-0.1.1.dist-info/RECORD
