Metadata-Version: 2.1
Name: CapiPy
Version: 0.1.1
Summary: CapiPy (Computer Assistance for Protein Immobilisation – Python) 
Home-page: https://github.com/drou0302/CapiPy
Author: David Roura Padrosa
Author-email: davidrourap@gmail.com
License: UNKNOWN
Platform: UNKNOWN
Classifier: Programming Language :: Python :: 3.6
Classifier: License :: OSI Approved :: GNU General Public License v3 (GPLv3)
Classifier: Operating System :: OS Independent
